jptax/__about__.py
jptax/__init__.py
jptax/insurance/__init__.py
jptax/insurance/dataframe.py
jptax/insurance/deduction.py
jptax/insurance/definitions.py
jptax/insurance/tables/r5ippan3.xlsx
jptax/insurance/tables/r6ippan3.xlsx
jptax-0.0.1.dist-info/METADATA
jptax-0.0.1.dist-info/WHEEL
jptax-0.0.1.dist-info/licenses/LICENSE.txt
jptax-0.0.1.dist-info/RECORD
