Metadata-Version: 2.3
Name: jptax
Version: 0.0.1
Project-URL: Documentation, https://github.com/harada88/jptax#readme
Project-URL: Issues, https://github.com/harada88/jptax/issues
Project-URL: Source, https://github.com/harada88/jptax
Author-email: HARADA <163368607+harada88@users.noreply.github.com>
License-Expression: MIT
License-File: LICENSE.txt
Classifier: Development Status :: 4 - Beta
Classifier: Programming Language :: Python
Classifier: Programming Language :: Python :: 3.8
Classifier: Programming Language :: Python :: 3.9
Classifier: Programming Language :: Python :: 3.10
Classifier: Programming Language :: Python :: 3.11
Classifier: Programming Language :: Python :: 3.12
Classifier: Programming Language :: Python :: Implementation :: CPython
Classifier: Programming Language :: Python :: Implementation :: PyPy
Requires-Python: >=3.8
Requires-Dist: openpyxl==3.1.2
Requires-Dist: pandas==2.2.1
Requires-Dist: pyarrow==15.0.1
Requires-Dist: xlrd==2.0.1
